{
  "kind": "collectionType",
  "collectionName": "products",
  "info": {
    "name": "product",
    "description": ""
  },
  "options": {
    "increments": true,
    "timestamps": true,
    "draftAndPublish": true
  },
  "attributes": {
    "name": {
      "type": "string"
    },
    "type": {
      "type": "string"
    },
    "description": {
      "type": "text"
    },
    "price": {
      "type": "decimal"
    },
    "Image": {
      "collection": "file",
      "via": "related",
      "allowedTypes": [
        "images"
      ],
      "plugin": "upload",
      "required": true
    },
    "category": {
      "model": "category",
      "via": "products"
    },
    "featured": {
      "type": "boolean"
    }
  }
}
